{
    "publication_date": "2025-08-21_02-44-04",
    "site_origin": "patriots.win",
    "url": "https://patriots.win/p/19BtL7QG2y/the-way-he-sits-is-so-gay/c",
    "category": "news",
    "original_title": "...the way he sits is so gay.\r\n  \u2014 The Donald",
    "article_summary": "Article discusses criticism of Canadian Prime Minister Justin Trudeau's seating posture, with users comparing it to a stereotypical gay man's way of sitting. The key takeaway is that the article is a thread of comments on social media criticizing and mocking Trudeau's seating posture.</s>"
}