{
    "publication_date": "2025-08-19_10-28-18",
    "site_origin": "rt.com",
    "url": "https://rt.com/news/623071-european-nato-states-continue-arm-ukraine/",
    "category": "news",
    "original_title": "Five takeaways from a week of Trump\u2019s Ukraine diplomacy \u2014 RT World News",
    "article_summary": "Western European leaders reaffirm support for Ukraine, pledging to send more military aid and seek NATO membership, despite Russian opposition. Trump continues diplomatic efforts to end the Ukraine conflict, urging Zelensky to show flexibility in talks with Putin.</s>"
}