{
    "publication_date": "2025-08-20_05-50-05",
    "site_origin": "www.ecns.cn",
    "url": "https://www.ecns.cn/news/cns-wire/2025-08-20/detail-iheummsh1681225.shtml",
    "category": "news",
    "original_title": "Students from BRI countries account for majority of Tsinghua University's international freshmen",
    "article_summary": "Tsinghua University's 2025 undergraduate intake sees a majority of international students hailing from Belt and Road partner countries. The university has moderately expanded its undergraduate intake this year, with over 300 international students from 50 countries and regions.</s>"
}