{
    "publication_date": "2025-08-20_05-50-05",
    "site_origin": "www.ecns.cn",
    "url": "https://www.ecns.cn/news/xuke.html",
    "category": "news",
    "original_title": "Ecns_404 - CHINA NEWS - Headlines, features, photo and videos from ecns.cn",
    "article_summary": "\"China News Headlines (May 7, 2018): Xizang's development accelerates due to modernization, Nanjing cultural venues experience visitor surge, Hainan expands tax incentives for top talent, and Taipei's mascot bear Bravo celebrates 10th birthday.\"</s>"
}