{
    "publication_date": "2025-08-20_07-05-58",
    "site_origin": "www.foxnews.com",
    "url": "https://www.foxnews.com/world/netanyahu-slams-australia-pm-says-he-betrayed-israel-abandoned-australias-jews",
    "category": "news",
    "original_title": "Australia and Israel trade diplomatic blows over Palestine recognition and visas | Fox News",
    "article_summary": "\"Israeli PM accuses Australian PM of betraying Israel, following Australia's recognition of Palestinian statehood and visa ban on Israeli lawmaker. Australia's Jewish community faces a surge in antisemitism, prompting calls for international intervention.\"</s>"
}