{
    "publication_date": "2025-08-21_04-44-03",
    "site_origin": "patriots.win",
    "url": "https://patriots.win/p/19BtL7SBFv/you-abused-your-security-clearan/c",
    "category": "news",
    "original_title": "You abused your security clearance by bad mouthing the President while having your clearance. You have been badmouthing him for years. \n\nNow you don\u2019t have a clearance. You signed the 2019 letter. Everything I said is accurate. \n\nEnjoy losing your Kentucky Senate race too, loser.  \u2014 The Donald",
    "article_summary": "Laura Loomer is accused of abusing a security clearance by badmouthing the President, but Joel Willett denies having a security clearance in 2019, casting doubt on the accusation.</s>"
}