{
    "publication_date": "2025-08-21_06-52-23",
    "site_origin": "cnn.com",
    "url": "https://cnn.com/2025/08/21/europe/nordstream-germany-italy-arrest-intl",
    "category": "news",
    "original_title": "Ukrainian man arrested over mysterious Nord Stream pipeline attacks | CNN",
    "article_summary": "Italian police have arrested a Ukrainian man suspected of coordinating the attacks on the Nord Stream pipelines, three years after the explosions that left gas billowing from the pipelines and sparked an international investigation. The arrest comes after Germany issued an international arrest warrant for another Ukrainian man suspected of causing damage to the pipelines.</s>"
}