{
    "publication_date": "2025-08-21_07-44-04",
    "site_origin": "patriots.win",
    "url": "https://patriots.win/p/19BtL7SSMy/the-kids-are-alright/c",
    "category": "news",
    "original_title": "The kids are alright  \u2014 The Donald",
    "article_summary": "\"Article discusses a controversial post about children rebelling against perceived liberal indoctrination, with comments criticizing the Obama and Biden administration for allowing \"transgender\" policies in schools, and advocating for home schooling and church education as alternatives.\"</s>"
}