{
    "publication_date": "2025-08-19_10-28-01",
    "site_origin": "patriots.win",
    "url": "https://patriots.win/p/19BtGXZNyL/milwaukee-hires-convicted-murder/c",
    "category": "news",
    "original_title": "Milwaukee Hires Convicted Murderer To Lead Violence Prevention Office  \u2014 The Donald",
    "article_summary": "Milwaukee hires a convicted murderer, who spent over 20 years in prison, to lead its Violence Prevention Office. The hire is seen as controversial, but supporters argue that his personal experience makes him uniquely qualified to interact with the community and prevent violence.</s>"
}