{
    "publication_date": "2025-08-21_02-44-20",
    "site_origin": "rt.com",
    "url": "https://rt.com/news/623346-us-russia-georgia-war/",
    "category": "news",
    "original_title": "Germany\u2019s Merz facing opposition over Ukraine troop plan \u2013 Bild \u2014 RT World News",
    "article_summary": "US abstains from condemning Russia for the 2008 war with Georgia at the UN, breaking past practices. The Georgian PM blames the previous regime for the conflict, while the current government is criticized for strained relations with the US. Meanwhile, Israel launches an operation to take over Gaza City, aiming for full control, with no immediate response from Hamas to a ceasefire proposal.</s>"
}