{
    "publication_date": "2025-08-21_02-44-20",
    "site_origin": "rt.com",
    "url": "https://rt.com/news/623296-white-house-sees-light-ukraine-conflict/",
    "category": "news",
    "original_title": "Germany\u2019s Merz facing opposition over Ukraine troop plan \u2013 Bild \u2014 RT World News",
    "article_summary": "\"US White House sees potential for lasting peace in Ukraine as President Trump pushes for talks between Trump and Zelensky, following a productive summit with Putin.\"</s>"
}