{
    "publication_date": "2025-08-20_05-34-42",
    "site_origin": "rt.com",
    "url": "https://rt.com/news/623284-trump-putin-zelensky-eu/",
    "category": "news",
    "original_title": "Netanyahu a \u2018war hero\u2019 \u2013 Trump \u2014 RT World News",
    "article_summary": "\"US-Russia talks in Anchorage reveal potential for territorial exchanges and security guarantees in Ukraine, while a Western-trained Ukrainian sabotage group planning attacks in Russia was busted by Russian law enforcement.\"</s>"
}